pip_timemachine/__init__.py
pip_timemachine/main.py
pip_timemachine/py.typed
pip_timemachine-0.2.3.dist-info/METADATA
pip_timemachine-0.2.3.dist-info/WHEEL
pip_timemachine-0.2.3.dist-info/entry_points.txt
pip_timemachine-0.2.3.dist-info/licenses/LICENSE
pip_timemachine-0.2.3.dist-info/RECORD
