Metadata-Version: 2.4
Name: pip-timemachine
Version: 0.2.3
Summary: Add your description here
Author-email: Damian Shaw <damian.peter.shaw@gmail.com>
License-File: LICENSE
Requires-Python: >=3.10
Requires-Dist: fastapi>=0.115.2
Requires-Dist: niquests>=3.9.1
Requires-Dist: packaging>=24.1
Requires-Dist: typer>=0.12.5
Requires-Dist: uvicorn>=0.32.0
Requires-Dist: uvloop>=0.21.0
Requires-Dist: werkzeug>=3.0.4
Requires-Dist: whenever~=0.9.5
